selectbreakcoint/__init__.py
selectbreakcoint/adaptive_lasso.py
selectbreakcoint/cointegration_tests.py
selectbreakcoint/critical_values.py
selectbreakcoint/results.py
selectbreakcoint/utils.py
selectbreakcoint/tests/__init__.py
selectbreakcoint/tests/test_selectbreakcoint.py
selectbreakcoint-1.0.0.dist-info/licenses/LICENSE
selectbreakcoint-1.0.0.dist-info/METADATA
selectbreakcoint-1.0.0.dist-info/WHEEL
selectbreakcoint-1.0.0.dist-info/top_level.txt
selectbreakcoint-1.0.0.dist-info/RECORD
