Metadata-Version: 2.4
Name: selectbreakcoint
Version: 1.0.0
Summary: Multiple Structural Breaks in Cointegrating Regressions: A Model Selection Approach
Author-email: "Dr. Merwan Roudane" <merwanroudane920@gmail.com>
Maintainer-email: "Dr. Merwan Roudane" <merwanroudane920@gmail.com>
License: MIT
Project-URL: Homepage, https://github.com/merwanroudane/selectbreakcoint
Project-URL: Documentation, https://github.com/merwanroudane/selectbreakcoint#readme
Project-URL: Repository, https://github.com/merwanroudane/selectbreakcoint.git
Project-URL: Issues, https://github.com/merwanroudane/selectbreakcoint/issues
Keywords: econometrics,cointegration,structural breaks,adaptive lasso,time series,unit root,model selection,penalized regression
Classifier: Development Status :: 4 - Beta
Classifier: Intended Audience :: Science/Research
Classifier: Intended Audience :: Financial and Insurance Industry
Classifier: License :: OSI Approved :: MIT License
Classifier: Operating System :: OS Independent
Classifier: Programming Language :: Python :: 3
Classifier: Programming Language :: Python :: 3.8
Classifier: Programming Language :: Python :: 3.9
Classifier: Programming Language :: Python :: 3.10
Classifier: Programming Language :: Python :: 3.11
Classifier: Programming Language :: Python :: 3.12
Classifier: Topic :: Scientific/Engineering
Classifier: Topic :: Scientific/Engineering :: Mathematics
Classifier: Topic :: Office/Business :: Financial
Requires-Python: >=3.8
License-File: LICENSE
Requires-Dist: numpy>=1.20.0
Requires-Dist: scipy>=1.7.0
Requires-Dist: scikit-learn>=1.0.0
Requires-Dist: pandas>=1.3.0
Requires-Dist: statsmodels>=0.13.0
Provides-Extra: dev
Requires-Dist: pytest>=7.0.0; extra == "dev"
Requires-Dist: pytest-cov>=4.0.0; extra == "dev"
Requires-Dist: black>=22.0.0; extra == "dev"
Requires-Dist: isort>=5.10.0; extra == "dev"
Requires-Dist: mypy>=0.990; extra == "dev"
Requires-Dist: flake8>=5.0.0; extra == "dev"
Provides-Extra: docs
Requires-Dist: sphinx>=5.0.0; extra == "docs"
Requires-Dist: sphinx-rtd-theme>=1.0.0; extra == "docs"
Requires-Dist: nbsphinx>=0.8.0; extra == "docs"
Provides-Extra: all
Requires-Dist: selectbreakcoint[dev,docs]; extra == "all"
Dynamic: license-file
